dbt/__init__.py
dbt/adapters/__init__.py
dbt/adapters/decodable/__init__.py
dbt/adapters/decodable/__version__.py
dbt/adapters/decodable/connections.py
dbt/adapters/decodable/handler.py
dbt/adapters/decodable/impl.py
dbt/adapters/decodable/relation.py
dbt/include/decodable/__init__.py
dbt/include/decodable/dbt_project.yml
dbt/include/decodable/macros/adapters.sql
dbt/include/decodable/macros/materializations/seed/helpers.sql
dbt/include/decodable/macros/materializations/seed/seed.sql
dbt/include/decodable/macros/materializations/table/create_table_as.sql
dbt/include/decodable/macros/materializations/table/table.sql
dbt/include/decodable/macros/materializations/test/get_test_sql.sql
dbt/include/decodable/macros/materializations/test/test.sql
dbt/include/decodable/macros/materializations/test/test_as_table.sql
dbt/include/decodable/macros/materializations/unsupported/incremental.sql
dbt/include/decodable/macros/materializations/unsupported/view.sql
dbt/include/decodable/macros/operations.sql
dbt/include/decodable/profile_template.yml
decodable/__init__.py
decodable/client/__init__.py
decodable/client/api.py
decodable/client/client.py
decodable/client/client_factory.py
decodable/client/types.py
decodable/config/__init__.py
decodable/config/client_config.py
decodable/config/profile.py
decodable/config/profile_reader.py
tests/__init__.py
tests/conftest.py
tests/functional/adapter/simple/fixtures.py
tests/functional/adapter/simple/test_simple_project.py
tests/unit/__init__.py
tests/unit/decodable/__init__.py
tests/unit/decodable/client/__init__.py
tests/unit/decodable/client/test_types.py
tests/unit/decodable/config/__init__.py
tests/unit/decodable/config/test_profile.yml
tests/unit/decodable/config/test_profile_reader.py
dbt_decodable-1.3.5.dist-info/LICENSE.txt
dbt_decodable-1.3.5.dist-info/METADATA
dbt_decodable-1.3.5.dist-info/WHEEL
dbt_decodable-1.3.5.dist-info/RECORD
