Metadata-Version: 2.1
Name: dbt-decodable
Version: 1.3.5
Summary: The Decodable adapter plugin for DBT
Home-page: https://github.com/decodableco/dbt-decodable
License: Apache2.0
Keywords: decodable,dbt
Author: Decodable
Author-email: info@decodable.co
Requires-Python: >=3.7.2
Classifier: License :: Other/Proprietary License
Classifier: Programming Language :: Python :: 3
Classifier: Programming Language :: Python :: 3.8
Classifier: Programming Language :: Python :: 3.9
Classifier: Programming Language :: Python :: 3.10
Classifier: Programming Language :: Python :: 3.11
Classifier: Programming Language :: Python :: 3.12
Requires-Dist: dbt-core (>=1.3.1,<1.4.0)
Project-URL: Repository, https://github.com/decodableco/dbt-decodable
